casec/__init__.py
casec/client.py
casec/command.py
casec/container.py
casec/formatter.py
casec/main.py
casec/operation.py
casec/parser.py
casec-0.2.1.dist-info/METADATA
casec-0.2.1.dist-info/WHEEL
casec-0.2.1.dist-info/entry_points.txt
casec-0.2.1.dist-info/top_level.txt
casec-0.2.1.dist-info/RECORD
