Metadata-Version: 2.1
Name: casec
Version: 0.2.1
Summary: CLI that converts the case of strings.
Home-page: UNKNOWN
Author: Allie Fitter
Author-email: afitter@cellcontrol.com
License: UNKNOWN
Platform: UNKNOWN
